README.md
setup.cfg
setup.py
bin/thus
bin/thus_completer_bash.sh
bin/thus_completer_zsh.sh
cloudonecli/__init__.py
cloudonecli/__main__.py
cloudonecli/clidriver.py
cloudonecli/session.py
cloudonecli/test.py
cloudonecli.egg-info/PKG-INFO
cloudonecli.egg-info/SOURCES.txt
cloudonecli.egg-info/dependency_links.txt
cloudonecli.egg-info/requires.txt
cloudonecli.egg-info/top_level.txt