Metadata-Version: 2.1
Name: cloudonecli
Version: 0.0.11
Summary: A cli tool for use with Trend Micro products.
Home-page: https://github.com/johnsobm/cloudonecli
Author: Brendan Johnson
Author-email: brendan.johnson@gmail.com
License: UNKNOWN
Platform: UNKNOWN
Classifier: Intended Audience :: Developers
Classifier: Intended Audience :: System Administrators
Classifier: Natural Language :: English
Classifier: License :: OSI Approved :: MIT License
Classifier: Programming Language :: Python
Classifier: Programming Language :: Python :: 3.6
Classifier: Programming Language :: Python :: 3.7
Classifier: Programming Language :: Python :: 3.8
Requires-Python: >=3.6
